[
    {
        "image": "921750927846313373_1325837722.jpg",
        "user": "todotoit",
        "link": "http://instagram.com/p/zKt5XRqo2d/"
    },
    {
        "image": "921750646895054228_1325837722.jpg",
        "user": "todotoit",
        "link": "http://instagram.com/p/zKt1Rnqo2U/"
    },
    {
        "image": "921750288844098955_1325837722.jpg",
        "user": "todotoit",
        "link": "http://instagram.com/p/zKtwEKKo2L/"
    },
    {
        "image": "921749885125561722_1325837722.jpg",
        "user": "todotoit",
        "link": "http://instagram.com/p/zKtqMKqo16/"
    },
    {
        "image": "921305008739208358_263078090.jpg",
        "user": "againstdemons",
        "link": "http://instagram.com/p/zJIgYvsEym/"
    }
]